grote/__init__.py
grote/app.py
grote/collections/__init__.py
grote/collections/base.py
grote/collections/config.yaml
grote/collections/load.py
grote/collections/translate.py
grote/config.py
grote/config.yaml
grote/event_logging.py
grote/functions/__init__.py
grote/functions/load.py
grote/functions/translate.py
grote/style.py
grote-0.1.11.dist-info/LICENSE
grote-0.1.11.dist-info/METADATA
grote-0.1.11.dist-info/WHEEL
grote-0.1.11.dist-info/entry_points.txt
grote-0.1.11.dist-info/RECORD
