Metadata-Version: 2.3
Name: grote
Version: 0.1.11
Summary: Groningen Translation Environment
License: Apache Software License 2.0
Keywords: translation environment,gradio
Author: Gabriele Sarti
Maintainer: Gabriele Sarti
Maintainer-email: gabriele.sarti996@gmail.com
Requires-Python: >=3.10,<3.12
Classifier: Development Status :: 3 - Alpha
Classifier: Intended Audience :: Science/Research
Classifier: License :: OSI Approved :: Apache Software License
Classifier: License :: Other/Proprietary License
Classifier: Operating System :: OS Independent
Classifier: Programming Language :: Python
Classifier: Programming Language :: Python :: 3
Classifier: Programming Language :: Python :: 3.10
Classifier: Programming Language :: Python :: 3.11
Classifier: Programming Language :: Python :: 3.8
Classifier: Programming Language :: Python :: 3.9
Classifier: Topic :: Scientific/Engineering :: Visualization
Provides-Extra: notebook
Requires-Dist: gradio (>=4.0,<5.0)
Requires-Dist: gradio_highlightedtextbox (>=0.0.13,<0.0.14)
Requires-Dist: ipykernel (>=6.19.2,<7.0.0) ; extra == "notebook"
Requires-Dist: ipywidgets (>=8.0.0rc2,<9.0.0) ; extra == "notebook"
Requires-Dist: jupyterlab (>=4.0.7,<5.0.0) ; extra == "notebook"
Requires-Dist: toml (>=0.10.2,<0.11.0)
Project-URL: Homepage, https://github.com/gsarti/grote
Project-URL: Repository, https://github.com/gsarti/grote
